odoo/addons/mis_template_financial_report/README.rst
odoo/addons/mis_template_financial_report/__init__.py
odoo/addons/mis_template_financial_report/__manifest__.py
odoo/addons/mis_template_financial_report/data/mis_report.xml
odoo/addons/mis_template_financial_report/data/mis_report_kpi.xml
odoo/addons/mis_template_financial_report/data/mis_report_style.xml
odoo/addons/mis_template_financial_report/data/mis_report_subreport.xml
odoo/addons/mis_template_financial_report/i18n/es.po
odoo/addons/mis_template_financial_report/i18n/fi.po
odoo/addons/mis_template_financial_report/i18n/fr.po
odoo/addons/mis_template_financial_report/i18n/it.po
odoo/addons/mis_template_financial_report/i18n/mis_template_financial_report.pot
odoo/addons/mis_template_financial_report/i18n/pt.po
odoo/addons/mis_template_financial_report/i18n/sl.po
odoo/addons/mis_template_financial_report/i18n/tr.po
odoo/addons/mis_template_financial_report/models/__init__.py
odoo/addons/mis_template_financial_report/models/mis_report_instance.py
odoo/addons/mis_template_financial_report/models/mis_report_kpi.py
odoo/addons/mis_template_financial_report/readme/CONFIGURE.md
odoo/addons/mis_template_financial_report/readme/CONTRIBUTORS.md
odoo/addons/mis_template_financial_report/readme/DESCRIPTION.md
odoo/addons/mis_template_financial_report/readme/ROADMAP.md
odoo/addons/mis_template_financial_report/readme/USAGE.md
odoo/addons/mis_template_financial_report/readme/newsfragments/.gitkeep
odoo/addons/mis_template_financial_report/static/description/icon.png
odoo/addons/mis_template_financial_report/static/description/index.html
odoo/addons/mis_template_financial_report/static/src/components/mis_report_widget.css
odoo/addons/mis_template_financial_report/static/src/components/mis_report_widget.xml
odoo/addons/mis_template_financial_report/static/src/css/report.css
odoo/addons/mis_template_financial_report/tests/__init__.py
odoo/addons/mis_template_financial_report/tests/test_mis_template_financial_report.py
odoo_addon_mis_template_financial_report-18.0.2.0.0.5.dist-info/METADATA
odoo_addon_mis_template_financial_report-18.0.2.0.0.5.dist-info/WHEEL
odoo_addon_mis_template_financial_report-18.0.2.0.0.5.dist-info/top_level.txt
odoo_addon_mis_template_financial_report-18.0.2.0.0.5.dist-info/RECORD
