Metadata-Version: 2.1
Name: odoo-addon-mis_template_financial_report
Version: 18.0.2.0.0.5
Requires-Python: >=3.10
Requires-Dist: odoo-addon-mis_builder==18.0.*
Requires-Dist: odoo==18.0.*
Summary: Profit & Loss / Balance sheet MIS templates
Home-page: https://github.com/OCA/account-financial-reporting
License: AGPL-3
Author: Hunki Enterprises BV,Odoo Community Association (OCA)
Author-email: support@odoo-community.org
Classifier: Programming Language :: Python
Classifier: Framework :: Odoo
Classifier: Framework :: Odoo :: 18.0
Classifier: License :: OSI Approved :: GNU Affero General Public License v3
